CrApsim/__init__.py
CrApsim-0.0.1a0.dist-info/DESCRIPTION.rst
CrApsim-0.0.1a0.dist-info/METADATA
CrApsim-0.0.1a0.dist-info/RECORD
CrApsim-0.0.1a0.dist-info/WHEEL
CrApsim-0.0.1a0.dist-info/entry_points.txt
CrApsim-0.0.1a0.dist-info/metadata.json
CrApsim-0.0.1a0.dist-info/top_level.txt
